{
  "target_horizon_h": 7,
  "feature_count": 40,
  "train_rows": 157777,
  "validation_rows": 35041,
  "train_logloss": 0.013373174450133394,
  "val_logloss": 0.01016444647358817,
  "selected_features": [
    "imf_solar_wind_density",
    "dst_dst_mean_6h",
    "imf_solar_wind_bt",
    "dst_dst",
    "imf_solar_wind_dynamic_pressure",
    "imf_solar_wind_temperature",
    "kp_kp_mean_6h",
    "imf_solar_wind_speed",
    "kp_kp_delta_6h",
    "cme_last_cme_shock_proxy",
    "sunspot_ssn_slope_27d",
    "kp_kp",
    "dst_dst_delta_6h",
    "sunspot_ssn_trend_1296h",
    "kp_kp_delta_1h",
    "h_4",
    "h_5",
    "cme_max_last_cme_shock_proxy_6h",
    "kp_kp_slope_6h",
    "cme_hours_since_last_cme",
    "h_6",
    "kp_kp_delta_3h",
    "dst_dst_delta_3h",
    "radio_flux_log_f107_mean_24h",
    "cme_max_last_cme_v_med_12h",
    "h_8",
    "kp_kp_max_6h",
    "h_3",
    "dst_dst_min_6h",
    "radio_flux_f107_anomaly_72h",
    "dst_dst_neg_frac_6h",
    "h_2",
    "radio_flux_log_f107",
    "imf_solar_wind_density_missing_flag",
    "h_1",
    "cme_cme_overtaking_flag",
    "radio_flux_f107_std_72h",
    "imf_solar_wind_density_source_id",
    "cme_effective_width",
    "radio_flux_f107"
  ],
  "best_params": {
    "n_estimators": 711,
    "max_depth": 5,
    "learning_rate": 0.011110413605600332,
    "subsample": 0.9386233091880705,
    "colsample_bytree": 0.6190478794055475,
    "min_child_weight": 2.7605313375614244,
    "gamma": 1.8847166854501347,
    "reg_alpha": 0.00022961716431955793,
    "reg_lambda": 6.167431610905627
  },
  "ensemble_size": 5
}